random_plus/__init__.py
random_plus/random_plus.py
random_plus-1.2.0.dist-info/LICENSE
random_plus-1.2.0.dist-info/METADATA
random_plus-1.2.0.dist-info/WHEEL
random_plus-1.2.0.dist-info/top_level.txt
random_plus-1.2.0.dist-info/RECORD
